[
    {
        "model": "technical_problems.Equipamento_Tipo",
        "pk": 1,
        "fields": {
            "nome": "BOX 1.0 HD (CABO)"
        }
    },
    {
        "model": "technical_problems.Tarifario",
        "pk": 1,
        "fields": {
            "nome": "6 Canais CABO"
        }
    },
    {
        "model": "technical_problems.Servico",
        "pk": 1,
        "fields": {
            "servico": "tv",
            "equipamento": 1,
            "tarifario": 1
        }
    },
    {
        "model": "technical_problems.Contrato",
        "fields": {
            "morada": "Rua da Universidade, Guimarães",
            "servicos": [1]
        }
    },
    {
        "model": "auth.User",
        "pk": 0,
        "fields": {
            "username": "933333333",
            "password": "111111111",
            "email": "teste@gmail.com",
            "first_name": "Testing",
            "last_name": "Name"
        }
    },
    {
        "model": "technical_problems.Cliente",
        "fields": {
            "user": 0,
            "contrato": "Rua da Universidade, Guimarães"
        }
    }
]
